notion/__init__.py
notion/auth/__init__.py
notion/client/__init__.py
notion/client/blocks.py
notion/client/databases.py
notion/client/pages.py
notion/orm/__init__.py
notion/orm/accessors/PageProperty.py
notion/orm/accessors/__init__.py
notion/orm/common/QueryFilter.py
notion/orm/common/QuerySort.py
notion/orm/common/SetProperty.py
notion/orm/common/__init__.py
notion/orm/config/__init__.py
notion/orm/extrators/Properties.py
notion/orm/extrators/__init__.py
notion/orm/mapping/__init__.py
notion/orm/mapping/database.py
notion/orm/mapping/registry.py
notion/orm/parsers/PageProperties.py
notion/orm/parsers/__init__.py
notion/orm/repositories/__init__.py
notion/orm/repositories/databases/CreateDatabasePage.py
notion/orm/repositories/databases/SearchPage.py
notion/orm/repositories/databases/SearchPageProperty.py
notion/orm/repositories/databases/__init__.py
notion/orm/repositories/pages/CreatePage.py
notion/orm/repositories/pages/GetPage.py
notion/orm/repositories/pages/GetPageProperty.py
notion/orm/repositories/pages/__init__.py
notion/schemas/__init__.py
notion/schemas/dto.py
notion/schemas/orm/__init__.py
notion/schemas/orm/database/DatabasesContainer.py
notion/schemas/orm/database/SearchPageProperty.py
notion/schemas/orm/database/__init__.py
notion/schemas/orm/properties/RichText.py
notion/schemas/orm/properties/__init__.py
notion/schemas/responses/__init__.py
notion/schemas/responses/databases/Query.py
notion/schemas/responses/databases/__init__.py
notion/schemas/responses/errors/Error.py
notion/schemas/responses/errors/__init__.py
notion/schemas/responses/pages/Page.py
notion/schemas/responses/pages/Parent.py
notion/schemas/responses/pages/__init__.py
notion/schemas/responses/pages/properties/RichText.py
notion/schemas/responses/pages/properties/__init__.py
notion/schemas/responses/users/Bot.py
notion/schemas/responses/users/Person.py
notion/schemas/responses/users/User.py
notion/schemas/responses/users/__init__.py
notion/schemas/responses/users/type/Bot.py
sdk_notion-0.1.0.dist-info/licenses/LICENSE
sdk_notion-0.1.0.dist-info/METADATA
sdk_notion-0.1.0.dist-info/WHEEL
sdk_notion-0.1.0.dist-info/top_level.txt
sdk_notion-0.1.0.dist-info/RECORD
