Metadata-Version: 2.4
Name: sdk-notion
Version: 0.1.0
Summary: Async Python SDK for the Notion API
Author: Eduardo Riguetto
License: MIT
Project-URL: Homepage, https://github.com/riguettodev/sdk-notion
Project-URL: Repository, https://github.com/riguettodev/sdk-notion
Requires-Python: >=3.9
License-File: LICENSE
Requires-Dist: httpx<1.0,>=0.25
Requires-Dist: pydantic<3.0,>=2.5
Dynamic: license-file
